[{"id": 980, "question": "What do people need to do to change their lives?", "options": ["face problems", "better themselves", "pay bills", "become disillusioned", "eat chicken"], "answer": 0}, {"id": 194, "question": "What is the primary purpose of cars?", "options": ["cost money", "slow down", "move people", "turn right", "get girls"], "answer": 2}, {"id": 921, "question": "What is a person looking for when completing puzzles or riddles?", "options": ["avoid pain", "compliments", "intellectual challenge", "passing grade", "attention"], "answer": 2}, {"id": 419, "question": "What kind of service is my body a part of when I'm no longer here?", "options": ["bodycam", "home", "coffin", "funeral", "graveyard"], "answer": 3}, {"id": 1066, "question": "The wood was still rough to the touch, what did the woodworker have to do?", "options": ["petrify", "sanded", "warp", "composted", "clean"], "answer": 1}, {"id": 151, "question": "What might someone believe in if they are cleaning clothes?", "options": ["feminism", "sanitation", "ruined", "wrinkles", "buttons to fall off"], "answer": 1}, {"id": 158, "question": "The man tried to reply to the woman, but he had difficulty keeping track of conversations that he didn't do what to?", "options": ["initiate", "ignore", "question", "answer", "ask"], "answer": 0}, {"id": 1023, "question": "What mall store sells jeans for a decent price?", "options": ["clothing store", "bedroom", "thrift store", "apartment", "gap"], "answer": 4}, {"id": 122, "question": "Who do professors work with?", "options": ["methods of facts", "teach courses", "wear wrinkled tweed jackets", "school students", "state facts"], "answer": 3}, {"id": 535, "question": "What is something children can do while traveling in a car?", "options": ["listen to music", "watch television", "play chess", "walk", "play basketball"], "answer": 0}, {"id": 1104, "question": "Animals come in all types, some fly thanks to their lightweight hollow what?", "options": ["tails", "bones", "eyes", "heads", "bodies"], "answer": 1}, {"id": 742, "question": "Most people who are family like to greet each other with a what?", "options": ["apartments", "listen to music", "have friends", "know what ophiolites", "hug"], "answer": 4}, {"id": 144, "question": "James thought of criminal justice like a computer program. It need to work right. What ideas might James not like?", "options": ["manual", "process information", "power down", "control model", "reason exists"], "answer": 3}, {"id": 129, "question": "Where could you find hundreds of thousands of home?", "options": ["field", "neighborhood", "star can", "city or town", "apartment building"], "answer": 3}, {"id": 703, "question": "This is an unavoidable physiological consequence of running. What is it?", "options": ["breathlessness", "increased heart rate", "falling down", "muscle bulk", "calluses"], "answer": 1}, {"id": 225, "question": "Writers with a great what can amass a large fortune?", "options": ["cookie", "bank", "real estate", "imagination", "bank roll"], "answer": 3}, {"id": 814, "question": "What do singers need to do before a show?", "options": ["warm up", "use microphones", "clear throats", "create music", "sound beautiful"], "answer": 0}, {"id": 1022, "question": "What is unlikely to get bugs on its windshield due to bugs' inability to reach it when it is moving?", "options": ["airplane", "scooter", "motorboat", "car", "motor vehicle"], "answer": 0}, {"id": 930, "question": "What very cold area in the east can a crab be found?", "options": ["fish market", "shallow waters", "atlantic ocean", "fresh water", "shore line"], "answer": 2}, {"id": 423, "question": "The man didn't do great in college, all his best memories were late night with his brothers at the what?", "options": ["big city", "fraternity house", "school", "building", "big town"], "answer": 1}, {"id": 1099, "question": "Where would you find people standing in a line outside?", "options": ["bus depot", "end of line", "opera", "neighbor's house", "meeting"], "answer": 0}, {"id": 974, "question": "After the weight cut he was worried about his energy levels, but this was part of participating in a what?", "options": ["work", "wrestle", "play sports", "matter", "sleep"], "answer": 1}, {"id": 1126, "question": "During the winter hunt he could hear every motion in the woods, this was because of the what of everything?", "options": ["being still", "silence", "stationary", "stillness", "standing still"], "answer": 3}, {"id": 1218, "question": "The man closed his eyes as the music played, what effect did the music have?", "options": ["coma", "enjoyable", "soothing", "universal", "good or bad"], "answer": 2}, {"id": 1106, "question": "Where is a lake likely to be glacial?", "options": ["michigan", "new york", "new york", "mountains", "countryside"], "answer": 3}, {"id": 1015, "question": "The weasel ran up away from danger, somebody joked only our first president could get him down from the what?", "options": ["washington dc", "ladder", "natural history museum", "cherry tree", "chicken coop"], "answer": 3}, {"id": 128, "question": "If a person is trying to keep something in their hand what should they do?", "options": ["complete collection", "own house", "procrastinate", "explode", "have to hold"], "answer": 4}, {"id": 953, "question": "What uses a ribbon to put words on paper?", "options": ["wrapping paper", "girl's hair", "bath", "floral arrangement", "typewriter"], "answer": 4}, {"id": 1210, "question": "What does a person with a what likely do?", "options": ["feel important", "trust himself", "own house", "electrical circuit", "know what time"], "answer": 4}, {"id": 1072, "question": "How might a automobile get off a freeway?", "options": ["exit ramp", "garage", "driveway", "repair shop", "stop light"], "answer": 0}, {"id": 245, "question": "The fact that Joe was able to memorize the list in spite of his apparent state proved that part of his brain was what?", "options": ["awake", "repeat", "sleeping", "concentrate", "read aloud"], "answer": 0}, {"id": 700, "question": "When you need to rest it's often because you have been doing what?", "options": ["action", "sleep", "sleeping", "in motion", "using energy"], "answer": 4}, {"id": 409, "question": "John farms anemone in what type of facility?", "options": ["michigan", "swimming pool", "atlantic ocean", "nursery", "gulf of mexico"], "answer": 3}, {"id": 896, "question": "What do young boys do on the ice in the winter?", "options": ["ski", "play hockey", "summer", "knit", "warm"], "answer": 1}, {"id": 1161, "question": "Copulating with the wrong partner may be ill advised, many diseases can be transferred that can cause different types of what?", "options": ["intense pleasure", "ejaculation", "period of rest", "enjoyment", "skin irritation"], "answer": 4}, {"id": 1152, "question": "Turkey only has a small northern part of their country located in part of the what?", "options": ["middle east", "oven", "balkan peninsula", "provide meat", "asia minor"], "answer": 2}, {"id": 791, "question": "James saw a kite flying in the sky. He traced the string back to its origin and found it. Where did the string begin?", "options": ["end of line", "hobby shop", "his hand", "toy store", "child's hand"], "answer": 4}, {"id": 665, "question": "Where is beer drank by people watching sticks and pucks?", "options": ["bottle", "refrigerator", "hockey game", "casino", "bar"], "answer": 2}, {"id": 737, "question": "Lawyers often talk in front of an audience where?", "options": ["work", "courtroom", "office building", "press charges", "theatre"], "answer": 1}, {"id": 81, "question": "A crane uses many a steel cable when working a what?", "options": ["abaft", "ship", "winch", "construction site", "building"], "answer": 3}, {"id": 92, "question": "Anybody could be hired in the kitchen, what was needed of them?", "options": ["forget", "oil squeaky hinge", "question authority", "wash dishes", "oik squeaky hinge"], "answer": 3}, {"id": 412, "question": "What would you do if you have curiosity but are blind and paralyzed?", "options": ["hear news", "analyse", "go somewhere", "examine thing", "see favorite show"], "answer": 1}, {"id": 1157, "question": "What type of fruit is easily broken in to sections?", "options": ["slide", "citrus", "band", "orchestra", "coconut"], "answer": 1}, {"id": 1137, "question": "James loved to surf but he wasn't good at it. He would always do what?", "options": ["wipe out", "enjoy yourself", "start fighting", "get wet", "drown"], "answer": 0}, {"id": 13, "question": "Aside from water and nourishment what does your dog need?", "options": ["bone", "charm", "petted", "lots of attention", "walked"], "answer": 3}, {"id": 860, "question": "Why would a small dog pant if it's hot outside?", "options": ["outside", "europe", "heat", "wet", "dog show"], "answer": 2}, {"id": 264, "question": "Where is one likely to find a brownstone?", "options": ["new york city", "subdivision", "ring", "hazleton", "live in"], "answer": 0}, {"id": 952, "question": "What may you have after awaking after a night of heavy drinking?", "options": ["get up", "discomfort", "discomfort", "headache", "shock"], "answer": 3}, {"id": 1043, "question": "What do people usually feel when falling in love?", "options": ["getting married", "pain", "happiness", "getting married", "suffering"], "answer": 2}, {"id": 928, "question": "Where do you keep extra clothing on a hike?", "options": ["person", "hamper", "closet", "upstairs", "backpack"], "answer": 4}]