[{"id": 3865, "question": "in a division sum , the remainder is 4 and the divisor is 2 times the quotient and is obtained by adding 2 to the thrice of the remainder . the dividend is :", "options": ["72", "90", "100", "110", "120"], "answer": 2}, {"id": 16809, "question": "in a class of 35 students 26 play football and play 20 long tennis , if 17 play above , many play neither ?", "options": ["6", "8", "10", "12", "14"], "answer": 0}, {"id": 14858, "question": "raman ' s salary was decreased by 50 % and subsequently increased by 50 % . how much percent does he loss", "options": ["75", "65", "45", "25", "35"], "answer": 3}, {"id": 32206, "question": "how many zeros does 135 ^ 19 x 42 ^ 17 end with ?", "options": ["0", "2", "5", "13", "17"], "answer": 4}, {"id": 25887, "question": "company x provides bottled water to its employees in 5 liter bottles , $ 2 each . at least how many 5 l bottles must company x buy monthly , so that new contract with $ 100 fixed monthly rate and $ 1 for 10 l bottle each paid off ? ( assume that no other costs apply )", "options": ["121", "125", "132", "134", "138"], "answer": 3}, {"id": 4139, "question": "the sum of number of boys and girls in a school is 400 . if the number of boys is x , then the number of girls becomes x % of the total number of students . the number of boys is ?", "options": ["50", "40", "60", "80", "70"], "answer": 3}, {"id": 11663, "question": "the dimensions of a rectangular solid are 4 inches , 6 inches , and 8 inches . if a cube , a side of which is equal to one of the dimensions of the rectangular solid , is placed entirely within thespherejust large enough to hold the cube , what the ratio of the volume of the cube to the volume within thespherethat is not occupied by the cube ?", "options": ["10 : 17", "2 : 5", "5 : 16", "25 : 7", "2 : 3"], "answer": 4}, {"id": 26976, "question": "the s . i . on a certain sum of money for 3 years at 8 % per annum is half the c . i . on rs . 4000 for 2 years at 10 % per annum . the sum placed on s . i . is ?", "options": ["3000", "2802", "1750", "2990", "2982"], "answer": 2}, {"id": 7778, "question": "the radius of a cone is 10 m , height 21 m . the volume of the cone is :", "options": ["2200', '", "1100', '", "5500', '", "3300', '", "1050']"], "answer": 0}, {"id": 6033, "question": "simplify 586645 * 9999", "options": ["5865863355", "5665863355", "4865863355", "4665863355", ""], "answer": 0}, {"id": 17803, "question": "in a certain corporation , there are 300 male employees and 100 female employees . it is known that 20 % of the male employees have advanced degrees and 40 % of the females have advanced degrees . if one of the 400 employees is chosen at random , what is the probability this employee has an advanced degree or is female ?", "options": ["1 / 20", "1 / 10", "1 / 5", "2 / 5", "3 / 4"], "answer": 3}, {"id": 20401, "question": "in town x , 72 percent of the population are employed , and 36 percent of the population are employed males . what percent of the employed people in town x are females ?", "options": ["16 %", "25 %", "32 %", "40 %", "50 %"], "answer": 4}, {"id": 2604, "question": "a man can do a job in 15 days . his father takes 20 days and his son finishes it in 15 days . how long will they take to complete the job if they all work together ?", "options": ["6.3", "6.9", "5.5", "6.1", "6.2"], "answer": 2}, {"id": 20461, "question": "the list price of an article is rs . 70 . a customer pays rs . 61.11 for it . he was given two successive discounts , one of them being 10 % . the other discount is ?", "options": ["8 %", "7 %", "10 %", "3 %", "4 %"], "answer": 3}, {"id": 21494, "question": "the speed at which a girl can row a boat in still water is 90 kmph . if she rows downstream , where the speed of current is 18 kmph , what time will he take to cover 330 metres ?", "options": ["11", "12", "13", "14", "15"], "answer": 0}, {"id": 19150, "question": "a store reported total sales of $ 400 million for february of this year . if the total sales for the same month last year was $ 320 million , approximately what was the percent increase in sales ?", "options": ["2 %", "17 %", "25 %", "65 %", "83 %"], "answer": 2}, {"id": 19209, "question": "the average age of 20 persons in a office is 15 years . out of these , the average age of 5 of them is 14 years and that of the other 9 persons is 16 years . the age of the 15 th person is ?", "options": ["79", "86", "95", "72", "80"], "answer": 1}, {"id": 4826, "question": "workers at a campaign office have 2000 fliers to send out . if they send out 1 / 10 of them in the morning and 1 / 4 of the remaining ones out during the afternoon , how many are left for the next day ?", "options": ["300", "1350", "1100", "1200", "1900"], "answer": 1}, {"id": 24061, "question": "what is the remainder when 43 ^ 88 is divided by 5 ?", "options": ["0", "1", "2", "3", "4"], "answer": 1}, {"id": 2427, "question": "a number is mistakenly divided by 5 instead of being multiplied by 5 . find the percentage change in the result due t this mistake .", "options": ["96 %", "95 %", "2400 %", "200 %", "400 %"], "answer": 0}, {"id": 31004, "question": "the speed of a boat in still water is 25 kmph . if it can travel 10 km upstream in 1 hr , what time it would take to travel the same distance downstream ?", "options": ["26 minut", "23 minut", "15 minut", "19 minut", "s"], "answer": 2}, {"id": 16784, "question": "the largest 5 digit number exactly divisible by 91 is ?", "options": ["99918", "99919", "99921", "99923", "99929"], "answer": 0}, {"id": 22651, "question": "the average weight of 5 person ' s increases by 10.0 kg when a new person comes in place of one of them weighing 40 kg . what might be the weight of the new person ?", "options": ["t", "76.5 kg", "90 kg", "", ""], "answer": 2}, {"id": 16812, "question": "a part - time employee whose hourly wage was decreased by 20 percent decided to increase the number of hours worked per week so that the employee ' s total income did not change . by what percent should the number of hours worked be increased ?", "options": ["12.5 %", "20 %", "25 %", "50 %", "100 %"], "answer": 2}, {"id": 684, "question": "a boatman selling a boat along river flow . if he sell boat in steal water at 3 m / sec and flow of river is 2 m / sec . how much time he will take to sell 100 m .", "options": ["30", "10", "15", "20", "25"], "answer": 3}, {"id": 24049, "question": "the cash difference between the selling prices of an book at a profit of 2 % and 4 % is $ 3 . the ratio of the two selling prices is :", "options": ["55 : 23", "52 : 33", "51 : 52", "45 : 53", "51 : 34"], "answer": 2}, {"id": 22690, "question": "a work can be completed by 12 boys in 24 days and 12 girls in 12 days . in how many days would the 6 boys and 6 girls working together complete the work ?", "options": ["12", "18", "16", "20", "24"], "answer": 2}, {"id": 28232, "question": "if it is assumed that 50 percent of those who receive a questionnaire by mail will respond and 300 responses are needed , what is the minimum number of questionnaires that should be mailed ?", "options": ["400", "420", "480", "500", "600"], "answer": 4}, {"id": 27621, "question": "? % of 360 = 93.6", "options": ["277", "36", "26", "72", ""], "answer": 2}, {"id": 4558, "question": "if 6 ! / 3 ^ x is an integer , what is the greatest possible value of x ?", "options": ["2", "4", "5", "6", "7"], "answer": 0}, {"id": 16871, "question": "the length of the bridge , which a train 100 metres long and travelling at 45 km / hr can cross in 30 seconds , is ?", "options": ["10 m", "16 m", "275 m", "19 m", "27 m"], "answer": 2}, {"id": 10782, "question": "n ^ ( n / 2 ) = 4 is true when n = 4 in the same way what is the value of n if n ^ ( n / 2 ) = 8 ?", "options": ["4", "8", "2", "6", "10"], "answer": 1}, {"id": 31814, "question": "we bought 85 hats at the store . blue hats cost $ 6 and green hats cost $ 7 . the total price was $ 530 . how many green hats did we buy ?", "options": ["36", "20", "40", "42", "44"], "answer": 1}, {"id": 22004, "question": "how many words , with or without meaning , can be formed using all letters of the word beautiful using each letter exactly once ?", "options": ["388,620", "388,260", "362,880", "352,880", "342,880"], "answer": 2}, {"id": 14063, "question": "the base of a triangular field is three times its altitude . if the cost of cultivating the field at rs . 24.68 per hectare be rs . 333.18 , find its base and height .", "options": ["100 m', '", "125 m', '", "150 m', '", "278 m', '", "300 m']"], "answer": 4}, {"id": 32450, "question": "the sum of three consecutive numbers is 252 . the greatest among these three number is :", "options": ["45", "80", "85", "55", "40"], "answer": 2}, {"id": 22901, "question": "4 women can complete a work in 7 days and 10 children take 14 days to complete the work . how many days will 5 women and 10 children take to complete the work ?", "options": ["ys", "6", "7", "", "1"], "answer": 0}, {"id": 28315, "question": "a can complete a project in 10 days and b can complete the same project in 30 days . if a and b start working on the project together and a quits 10 days before the project is completed , in how many days will the project be completed ?", "options": ["ys", "15", "26.67", "", "12"], "answer": 1}, {"id": 2198, "question": "in a simultaneous throw of pair of dice . find the probability of getting the total more than 7", "options": ["5 / 7", "4 / 7", "5 / 12", "4 / 7", "1 / 6"], "answer": 2}, {"id": 12817, "question": "if a town of 45,000 people is growing at a rate of approx . 1 % per year , the population of the town in 5 years will be closest to ?", "options": ["46000", "47000", "48000", "49000", "50000"], "answer": 0}, {"id": 28389, "question": "a rectangular region has a fence along three sides and a wall along the fourth side . the fenced side opposite the wall is twice the length of each of the other two fenced sides . if the area of the rectangular region is 200 square feet , what is the total length of the fence , in feet ?", "options": ["10', '", "20', '", "30', '", "40', '", "80']"], "answer": 3}, {"id": 10608, "question": "if x ^ 2 + ( 1 / x ^ 2 ) = 9 , x ^ 4 + ( 1 / x ^ 4 ) = ?", "options": ["10", "11", "12", "14", "79"], "answer": 4}, {"id": 28040, "question": "in may mrs lee ' s earnings were 70 percent of the lee family ' s total income . in june mrs lee earned 20 percent more than in may . if the rest of the family ' s income was the same both months , then , in june , mrs lee ' s earnings were approximately what percent of the lee family ' s total income ?", "options": ["64 %", "68 %", "72 %", "74 %", "83 %"], "answer": 3}, {"id": 19732, "question": "two airplanes fly the same exact route from atlanta to chicago . plane a flies 200 mph while plane b flies 300 mph ( assume that simple model versus actual acceleration / deceleration near the airports ) . if plane a took off exactly 40 minutes before plane b , after how many minutes will plane b overtake plane a ?", "options": ["65", "80", "90", "115", "120"], "answer": 1}, {"id": 30921, "question": "united telephone charges a base rate of $ 9.00 for service , plus an additional charge of $ 0.25 per minute . atlantic call charges a base rate of $ 12.00 for service , plus an additional charge of $ 0.20 per minute . for what number of minutes would the bills for each telephone company be the same ?", "options": ["2 minut", "10 minut", "20 minut", "40 minut", "s"], "answer": 4}, {"id": 1042, "question": "a train is 435 meter long is running at a speed of 45 km / hour . in what time will it pass a bridge of 140 meter length", "options": ["20 s", "30 s", "on", "s", ""], "answer": 2}, {"id": 23597, "question": "there are 400 female managers in a certain company . find the total number of female employees in the company , if 2 / 5 of all the employees are managers and 2 / 5 of all male employees are managers .", "options": ["800", "900", "1000", "1100", ""], "answer": 2}, {"id": 9066, "question": "the ratio of number of boys and girls in a school is 2 : 5 . if there are 210 students in the school , find the number of girls in the school ?", "options": ["150", "250", "300", "370", "280"], "answer": 0}, {"id": 32815, "question": "if 16 percent of the students at a certain school went to a camping trip and took more than $ 100 , and 75 percent of the students who went to the camping trip did not take more than $ 100 , what percentage of the students at the school went to the camping trip ?", "options": ["95", "90", "85", "80", "64"], "answer": 4}, {"id": 20763, "question": "what percent is 1 gm of 1 kg ?", "options": ["0.1 %", "1 %", "1.5 %", "2 %", "3 %"], "answer": 0}]