[{"id": 1461, "question": "the principal that amounts to rs . 4903 in 3 years at 6 1 / 4 % per annum c . i . compounded annually , is ?", "options": ["s . 3096", "s . 4076", "s . 4085", "s . 4096", "s . 5096"], "answer": 1}, {"id": 17533, "question": "rs . 1690 is divided so that 4 times the first share , thrice the 2 nd share and twice the third share amount to the same . what is the value of the third share ?", "options": ["s . 528", "s . 542", "s . 780", "s . 540", "s . 549"], "answer": 2}, {"id": 2627, "question": "the sum of four consecutive even integers is 1284 . the greatest of them is :", "options": ["324", "342", "364", "382", ""], "answer": 0}, {"id": 30195, "question": "a can give b 80 meters start and c 200 meters start in a kilometer race . how much start can b give c in a kilometer race ?", "options": ["130.12", "130.43", "130.22", "111.0", "111.12"], "answer": 1}, {"id": 16117, "question": "a train 455 m long , running with a speed of 63 km / hr will pass a tree in ?", "options": ["22 s", "16 s", "", "39 s", ""], "answer": 3}, {"id": 3803, "question": "if the space diagonal of cube c is 5 inches long , what is the length , in inches , of the diagonal of the base of cube c ?", "options": ["5 / ( \u221a 6 )', '", "5 \u00b7 \u221a ( 2 / 3 )', '", "5 \u00b7 \u221a ( 3 / 2 )', '", "5 \u00b7 \u221a 3', '", "5 \u00b7 \u221a 6']"], "answer": 1}, {"id": 30696, "question": "p and q can complete a work in 15 days and 10 days respectively . they started the work together and then q left after 2 days . p alone completed the remaining work . the work was finished in - - - days .", "options": ["12", "16", "20", "24", "28"], "answer": 0}, {"id": 29340, "question": "what is the difference between 62 % of 150 nd 20 % of 250 .", "options": ["16", "17", "43", "19", "20"], "answer": 2}, {"id": 8308, "question": "if the population of a certain country increases at the rate of one person every 20 seconds , by how many persons does the population increase in 1 hour ?", "options": ["100", "120", "150", "180", "160"], "answer": 3}, {"id": 8534, "question": "in how many ways 4 boys and 5 girls can be seated in a row so that they are alternate .", "options": ["144", "288", "12", "256", "2880"], "answer": 4}, {"id": 17286, "question": "for any positive integer n , the sum of the first n positive integers equals n ( n + 1 ) / 2 . what is the sum x of all the even integers between 99 and 301 ?", "options": ["10,100", "20,200", "22,650", "40,200", "45,150"], "answer": 1}, {"id": 19490, "question": "if ( - 4 ) ^ ( 6 x ) = 4 ^ ( 30 + x ) and x is an integer , what is the value of x ?", "options": ["5", "4", "3", "2", "6"], "answer": 4}, {"id": 10066, "question": "the consumption of diesel per hour of a bus varies directly as square of its speed . when the bus is travelling at 60 kmph its consumption is 1 litre per hour . if each litre costs $ 30 and other expenses per hous is $ 20 , then what would be the minimum expenditure required to cover a distance of 600 km ?", "options": ["500", "450", "600", "650", "750"], "answer": 0}, {"id": 10030, "question": "if a \u2013 8 = b , then determine the value of | a - b | - | b - a | .", "options": ["16", "0", "4", "2", "1"], "answer": 1}, {"id": 6767, "question": "robert ate 7 chocolates , nickel ate 3 chocolates . how many more chocolates did robert ate than nickel ?", "options": ["4", "7", "9", "5", "2"], "answer": 0}, {"id": 27846, "question": "the average age of a class of 20 students is 14 years . the average increased by 2 when the teacher ' s age also included . what is the age of the teacher ?", "options": ["rs", "41 y", "42 y", "43 y", ""], "answer": 4}, {"id": 14952, "question": "the cost of painting the whole surface area of a cube at the rate of 13 paise per sq . cm is rs . 343.98 . then the volume of the cube is", "options": ["8500", "9000", "m 3', '", "9261", "']"], "answer": 3}, {"id": 7513, "question": "3 people have $ 28 , $ 72 , and $ 98 , respectively . if they pool their money then redistribute it among them , what is the maximum value for the median amount of money ?", "options": ["$ 72", "$ 85", "$ 99", "$ 101", "$ 202"], "answer": 2}, {"id": 6282, "question": "the radius of a wheel is 22.4 cm . what is the distance covered by the wheel in making 200 resolutions .", "options": ["271.34 m", "281.34 m", "291.34 m", "301.34 m", "311.34 m"], "answer": 1}, {"id": 14187, "question": "if the sum of the first n positive integers is s , what is the sum of the first n positive integers divisible by 5 , in terms of s ?", "options": ["s / 2", "s", "2 s", "2 s + 2", "5 s"], "answer": 4}, {"id": 15559, "question": "a 600 m long train crosses a tree in 60 sec , how much time will it take to pass a platform 450 m long ?", "options": ["288", "190", "188", "188", "105"], "answer": 4}, {"id": 14684, "question": "20 beavers , working together in a constant pace , can build a dam in 3 hours . how many v hours will it take 12 beavers that work at the same pace , to build the same dam ?", "options": ["2 .", "v = 4 .", "v = 5 .", "v = 6 .", "8 ."], "answer": 2}, {"id": 20633, "question": "if 5 < x < 12 and y = x + 3 , what is the greatest possible integer value of x + y ?", "options": ["23", "24", "25", "26", "27"], "answer": 3}, {"id": 3133, "question": "if the horse can run 10 miles / hour , how many days would it take for a horse to run from new york city to washington . d . c . ? ( 240 miles from nyc to d . c . )", "options": ["0.6", "0.8", "1", "1.2", "1.4"], "answer": 2}, {"id": 23562, "question": "one side of a rectangular field is 15 m and one of its diagonal is 17 m . find the area of field ?", "options": ["110", "120", "130", "140", "150"], "answer": 1}, {"id": 29569, "question": "the effective annual rate of interest corresponding to a nominal rate of 6 % per annum payable half - yearly is ?", "options": ["6.99 %", "6.89 %", "6.08 %", "6.09 %", "6.19 %"], "answer": 3}, {"id": 32073, "question": "the speed of a car is 90 km in the first hour and 75 km in the second hour . what is the average speed of the car ?", "options": ["89 kmph", "82.5 kmph", "75 kmph", "65 kmph", "77 kmph"], "answer": 1}, {"id": 31809, "question": "find a two digit number , given that the sum of the digits is 12 and the difference of the digits is 6 . ?", "options": ["41", "46", "42", "46", "47"], "answer": 0}, {"id": 9517, "question": "a shopkeeper sold an article offering a discount of 5 % and earned a profit of 27.3 % . what would have been the percentage of profit earned if no discount had been offered ?", "options": ["28.5", "27.675", "30", "34 %", ""], "answer": 3}, {"id": 3236, "question": "how many even integers n , such that 20 < = n < = 220 are of the form 3 k + 4 , where k is any natural number ?", "options": ["28", "31", "34", "37", "40"], "answer": 2}, {"id": 14615, "question": "when a certain number x is divided by 63 , the remainder is 27 . what is the remainder when x is divided by 8 ?", "options": ["2", "3", "4", "5", "6"], "answer": 1}, {"id": 17396, "question": "carol spends 1 / 4 of her savings on a stereo and 1 / 3 less than she spent on the stereo for a television . what fraction of her savings did she spend on the stereo and television ?", "options": ["1 / 4", "2 / 7", "5 / 12", "1 / 2", "7 / 12"], "answer": 2}, {"id": 27249, "question": "the average of runs of a cricket player of 10 innings was 30 . how many runs must he make in his next innings so as to increase his average of runs by 4 ?", "options": ["87", "74", "10", "76", "17"], "answer": 1}, {"id": 27245, "question": "carol and jordan draw rectangles of equal area . if carol ' s rectangle measures 12 inches by 15 inches and jordan ' s rectangle is 9 inches long , how wide is jordan ' s rectangle , in inches ?", "options": ["17", "18", "19", "20", "21"], "answer": 3}, {"id": 25993, "question": "the average of marks obtained by 120 boys was 35 . if the average of marks of passed boys was 39 and that of failed boys was 15 , the number of boys who passed the examination is ?", "options": ["100", "110", "120", "130", "140"], "answer": 0}, {"id": 28214, "question": "a new tower has just been built at the verbico military hospital ; the number of beds available for patients at the hospital is now 2 times the number available before the new tower was built . currently , 1 / 3 of the hospital ' s original beds , as well as 1 / 5 of the beds in the new tower , are occupied . for the purposes of renovating the hospital ' s original wing , all of the patients in the hospital ' s original beds must be transferred to beds in the new tower . if patients are neither admitted nor discharged during the transfer , what fraction of the beds in the new tower will be unoccupied once the transfer is complete ?", "options": ["11 / 30", "29 / 60", "17 / 30", "19 / 30", "7 / 15"], "answer": 4}, {"id": 15754, "question": "a train 280 m long , running with a speed of 72 km / hr will pass a tree in ?", "options": ["17 s", "16 s", "", "14 s", ""], "answer": 3}, {"id": 7761, "question": "two trains start from p and q respectively and travel towards each other at a speed of 50 km / hr and 40 km / hr respectively . by the time they meet , the first train has traveled 100 km more than the second . the distance between p and q is ?", "options": ["900 km", "300 km", "700 km", "800 km", "100 km"], "answer": 0}, {"id": 28248, "question": "if ( 18 ^ a ) * 9 ^ ( 3 a \u2013 1 ) = ( 2 ^ 2 ) ( 3 ^ b ) and a and b are positive integers , what is the value of a ?", "options": ["22", "11", "9", "6", "2"], "answer": 4}, {"id": 10787, "question": "pipe p can drain the liquid from a tank in 3 / 4 the time that it takes pipe q to drain it and in 3 / 3 the time that it takes pipe r to do it . if all 3 pipes operating simultaneously but independently are used to drain liquid from the tank , then pipe q drains what portion of the liquid from the tank ?", "options": ["9 / 29", "8 / 23", "3 / 8", "3 / 11", "3 / 4"], "answer": 3}, {"id": 30258, "question": "if below equation are true 24 $ 6 = 64 35 $ 5 = 87 63 $ 7 = 99 by using same logic what is the value of the below question 88 $ 8 = ?", "options": ["1621", "1711", "1611", "1511", "1311"], "answer": 2}, {"id": 19500, "question": "if the area of a circle is 49 pi square feet , find its circumference .", "options": ["14 pi f", "28 pi f", "38 pi f", "48 pi f", "t"], "answer": 0}, {"id": 27802, "question": "a large tank can filled by a and b in 30 minutes and 45 minutes respectively . how many minutes will it take to fill the tanker from empty state if b is used for half the time and a and b fill it together for the other half ?", "options": ["30 min", "20 min", "25 min", "40 min", "45 min"], "answer": 4}, {"id": 12432, "question": "a store reduced the price of all items in the store by 15 % on the first day and by another 10 % on the second day . the price of items on the second day was what percent of the price before the first reduction took place ?", "options": ["76.5", "80.9", "81.0", "81.1", "81.9"], "answer": 0}, {"id": 2947, "question": "anne earned $ 3 an hour baby - sitting , and $ 4 an hour working in the garden . last week she did baby - sitting for 5 hours and garden work for 3 hours . how much more money does she need to buy a game that costs $ 35 ?", "options": ["$ 8", "$ 12", "$ 6", "$ 21", "$ 10"], "answer": 0}, {"id": 3426, "question": "each child has 2 pencils and 13 skittles . if there are 15 children , how many pencils are there in total ?", "options": ["30", "12", "18", "22", "08"], "answer": 0}, {"id": 20695, "question": "an escalator moves towards the top level at the rate of 11 ft . sec and its length is 126 feet . if a person walks on the moving escalator at the rate of 3 feet per second towards the top level , how much time does he take to cover the entire length .", "options": ["14 s", "10 s", "", "8 s", ""], "answer": 4}, {"id": 21852, "question": "the distance from city a to city b is 220 miles . while driving from city a to city b , bob drives at a constant speed of 40 miles per hour . alice leaves city a 30 minutes after bob . what is the minimum constant speed in miles per hour that alice must exceed in order to arrive in city b before bob ?", "options": ["44", "48", "50", "52", "54"], "answer": 0}, {"id": 4368, "question": "at a local appliance manufacturing facility , the workers received a 30 % hourly pay raise due to extraordinary performance . if one worker decided to reduce the number of hours that he worked so that his overall pay would remain unchanged , by approximately what percent would he reduce the number of hours that he worked ?", "options": ["83 %", "80 %", "23 %", "17 %", "12 %"], "answer": 2}, {"id": 20964, "question": "the salary of a typist was at first raised by 10 % and then the same was reduced by 5 % . if he presently draws rs . 2090 . what was his original salary ?", "options": ["2277", "2999", "1000", "2651", "2000"], "answer": 4}]