[{"id": 19790, "question": "a luxury liner , queen marry ii , is transporting several cats as well as the crew ( sailors , a cook , and one - legged captain ) to a nearby port . altogether , these passengers have 16 heads and 45 legs . how many cats does the ship host ?", "options": ["3", "6", "9", "8", "7"], "answer": 4}, {"id": 4156, "question": "a store owner estimates that the average price of type a products will increase by 20 % next year and that the price of type b products will increase by 11 % next year . this year , the total amount paid for type a products was $ 3500 and the total price paid for type b products was $ 8600 . according to the store owner ' s estimate , and assuming the number of products purchased next year remains the same as that of this year , how much will be spent for both products next year ?", "options": ["$ 13,746", "$ 15,325", "$ 16,000", "$ 16,225", "$ 17,155"], "answer": 0}, {"id": 29896, "question": "find the mean proportional between 49 & 64 ?", "options": ["59", "61", "56", "65", "67"], "answer": 2}, {"id": 338, "question": "the diameters of two spheres are in the ratio 1 : 2 what is the ratio of their surface area ?", "options": ["1 : 0', '", "1 : 4', '", "1 : 6', '", "1 : 2', '", "1 : 1']"], "answer": 1}, {"id": 9662, "question": "if a car went the first third of the distance at 80 kmh , the second third at 24 kmh , and the last third at 60 kmh , what was the average speed of the car for the entire trip ?", "options": ["36 kmh", "40 kmh", "42 kmh", "44 kmh", "50 kmh"], "answer": 2}, {"id": 13244, "question": "a train running at the speed of 240 km / hr crosses a pole in 21 seconds . what is the length of the train ?", "options": ["1300 m", "1350 m", "1400 m", "1450 m", "1500 m"], "answer": 2}, {"id": 25149, "question": "a man can row 9 kmph in still water . when the river is running at 1.2 kmph , it takes him 1 hour to row to a place and back . what is the total distance traveled by the man ?", "options": ["6.24 km", "6 km", "8.84 km", "5.66 km", "10 km"], "answer": 2}, {"id": 1125, "question": "among the two clocks , clock a gains 20 seconds per minute . if clock a and b are set at 2 0 ' clock , when clock a is at 7 : 20 , what does clock b show ?", "options": ["5 : 30", "6 : 00", "5 : 45", "6 : 20", "3 : 30"], "answer": 1}, {"id": 31767, "question": "how many integers between 400 and 1000 are there such that their unit digit is odd ?", "options": ["250", "150", "300", "400", "450"], "answer": 2}, {"id": 28991, "question": "the length of a room is 5.5 m and width is 3.75 m . what is the cost of paying the floor by slabs at the rate of $ 400 per sq . metre .", "options": ["$ 8250", "$ 8350", "$ 8650", "$ 8450", "$ 8500"], "answer": 0}, {"id": 3179, "question": "the cost of registration at a professional association meeting was $ 50 per person ; a lunch for registrants only was available for an additional $ 22 per person . if the number of registrants who paid for lunch was 50 more than the number who did not , and if receipts for registration and lunch totaled $ 82,900 , how many people paid just for registration at the meeting ?", "options": ["700", "650", "1,300", "1,500", "1,800"], "answer": 1}, {"id": 31745, "question": "in a 200 meter race a beats b by 35 meters in 7 seconds . a ' s time over the cause is ?", "options": ["47 s", "40 s", "", "33 s", ""], "answer": 3}, {"id": 2008, "question": "x , y , and z are all unique numbers . if x is chosen randomly from the set { 10 , 11 } and y and z are chosen randomly from the set { 20 , 21 , 22 , 23 } , what is the probability that x and y are prime and z is not ?", "options": ["1 / 5", "3 / 20", "1 / 8", "3 / 10", "1 / 10"], "answer": 2}, {"id": 3554, "question": "a certain roller coaster has 4 cars , and a passenger is equally likely to ride in any 1 of the 4 cars each time that passenger rides the roller coaster . if a certain passenger is to ride the roller coaster 4 times , what is the probability that the passenger will ride in each of the 4 cars ?", "options": ["0", "1 / 9", "2 / 9", "3 / 32", "1"], "answer": 3}, {"id": 23342, "question": "there are 20 students in a class . in how many different ways can a committee of 3 students be formed ?", "options": ["650", "730", "980", "1140", "1480"], "answer": 3}, {"id": 22353, "question": "if both 5 ^ 2 and 3 ^ 4 are factors of the number a * 4 ^ 3 * 6 ^ 2 * 13 ^ 11 , then what is the smallest possible value of a ?", "options": ["80", "120", "150", "225", "300"], "answer": 3}, {"id": 28810, "question": "a batsman scored 1 runs in his 18 th innings and that makes his average 18 . find his average upto the 17 th innings ?", "options": ["19", "20", "21", "22", "23"], "answer": 0}, {"id": 25927, "question": "what is the smallest positive integer x , such that 5000 x is a perfect cube ?", "options": ["4", "6", "8", "25", "18"], "answer": 3}, {"id": 32351, "question": "company z has 50 employees . if the number of employees having birthdays on wednesday is more than the number of employees having birthdays on any other day of the week , each of which have same number of birth - days , what is the minimum number of employees having birthdays on wednesday .", "options": ["6", "7", "8", "9", "12"], "answer": 4}, {"id": 15484, "question": "sale of rs 6835 , rs . 9927 , rs . 6855 , rs . 7230 and rs . 6562 for 5 consecutive months . how much sale must he have in the sixth month so that he gets an average sale of rs , 6600 ?", "options": ["5591", "2477", "2877", "2676", "1881"], "answer": 0}, {"id": 24416, "question": "at the end of year x , automobile installment credit accounted for 36 % of all outstanding consumer installment credit . at that time automobile finance companies extended $ 75 billion of credit , or 1 / 2 of the automobile installment credit . how many billion dollars of consumer installment credit was outstanding at that time ?", "options": ["412.16", "150", "400", "416.67", "420.34"], "answer": 3}, {"id": 27420, "question": "gary \u2019 s gas station serves an average of 16 cars per hour on saturdays , 10 cars per hour on sundays , and 9 cars per hour on all other days of the week . if the station is open from 6 a . m . to 10 p . m . every day , how many cars does gary \u2019 s station serve over the course of a typical week ?", "options": ["1,136", "1,200", "1,240", "1,280", "1,320"], "answer": 0}, {"id": 6507, "question": "when positive integer k is divided by 5 , the remainder is 2 . when k is divided by 6 , the remainder is 5 . if k is less than 41 , what is the remainder when k is divided by 7 ?", "options": ["3", "4", "5", "6", "7"], "answer": 0}, {"id": 29612, "question": "the dimensions of a field are 16.5 m by 10 m . a pit 10 m long , 5.5 m wide and 4 m deep is dug in one corner of the field and the earth removed has been evenly spread over the remaining area of the field . what will be the rise in the height of field as a result of this operation ?", "options": ["2 m", "3 m", "1 m", "2.5 m", "3.5 m"], "answer": 0}, {"id": 188, "question": "in an electric circuit , two resistors with resistances 3 ohm and 5 ohm are connected in parallel . in this case , if r is the combined resistance of these two resistors , then the reciprocal of r is equal to the sum of the reciprocals of two resistors . what is the value ?", "options": ["15 ohms', '", "15 / 8 ohms', '", "1 / 8 ohms', '", "8 / 15 ohms', '", "8 ohms']"], "answer": 1}, {"id": 23832, "question": "in 6 successive games , a baseball team scored 1 runs once , 4 runs twice , and 5 runs 3 times . what was the average ( arithmetic mean ) number of runs the team scored per game over the 6 - game period ?", "options": ["8", "7", "6", "5", "4"], "answer": 4}, {"id": 19487, "question": "sachin is younger than rahul by 7 years . if the ratio of their ages is 5 : 12 , find the age of sachin", "options": ["9", "24.8", "2", "3", "5"], "answer": 4}, {"id": 22862, "question": "what is the square root of 261,121 ?", "options": ["476", "489", "497", "511", "524"], "answer": 3}, {"id": 16022, "question": "the l . c . m of two numbers is 48 . the numbers are in the ratio 4 : 3 . the sum of numbers is :", "options": ["28", "30", "40", "50", "60"], "answer": 0}, {"id": 17258, "question": "the ratio of investments of two partners p and q is 7 : 5 and the ratio of their profits is 7 : 9 . if p invested the money for 5 months , find for how much time did q invest the money ?", "options": ["9", "17", "13", "10", "12"], "answer": 0}, {"id": 4265, "question": "the tax on a commodity is diminished by 22 % and its consumption increased by 11 % . the effect on revenue is ?", "options": ["8", "6", "5", "4", "2"], "answer": 4}, {"id": 27341, "question": "if a 6 cm cube is cut into 1 cm cubes , then what is the percentage increase in the surface area of the resulting cubes ?", "options": ["300 %", "400 %", "500 %", "600 %", "750 %"], "answer": 2}, {"id": 15519, "question": "a 250 m long train is running at a speed of 55 km / hr . it crossed a platform of length 520 m in ?", "options": ["", "ov", "", "50.4 s", ""], "answer": 3}, {"id": 27689, "question": "david has $ 2,400 at the beginning of his trip , after spending money , he still has exactly $ 800 less than he spent on the trip . how much money does john still have ?", "options": ["$ 200", "$ 400", "$ 600", "$ 800", "$ 1,200"], "answer": 3}, {"id": 8874, "question": "80 is increased by 50 % . find the final number .", "options": ["100", "110", "120", "30", "160"], "answer": 2}, {"id": 15311, "question": "two numbers have a h . c . f of 9 and a product of two numbers is 1800 . find the l . c . m of the two numbers ?", "options": ["200", "150", "160", "170", "180"], "answer": 0}, {"id": 24212, "question": "an industrial loom weaves 0.128 metres of cloth every second . approximately , how many seconds will it take for the loom to weave 25 metres of cloth ?", "options": ["488", "204", "195", "178", "133"], "answer": 2}, {"id": 20708, "question": "two numbers are respectively 17 % and 30 % more than a third number . the percentage that is first of the second is ?", "options": ["75 %", "80 %", "85 %", "70 %", "90 %"], "answer": 4}, {"id": 19870, "question": "convert 150 inches into centimeter ?", "options": ["312", "381", "m", "310", "354"], "answer": 1}, {"id": 18122, "question": "the average marks of a class of 25 students is 40 and that of another class of 30 students is 60 . find the average marks of all the students ?", "options": ["52.6", "52.4", "52.1", "50.9", "52.9"], "answer": 3}, {"id": 4188, "question": "the sum of digits of a two digit number is 10 , the difference between the digits is 6 . find the number", "options": ["85", "94", "82", "72", ""], "answer": 2}, {"id": 26812, "question": "a dealer purchases 15 articles for rs . 25 and sells 12 articles for rs . 33 . find the profit percentage ?", "options": ["65 %", "50 %", "59 %", "40 %", "53 %"], "answer": 0}, {"id": 20563, "question": "two assembly line inspectors , lauren and steven , inspect widgets as they come off the assembly line . if lauren inspects every fifth widget , starting with the fifth , and steven inspects every third , starting with the third , how many of the 95 widgets produced in the first hour of operation are not inspected by either inspector ?", "options": ["50", "43", "45", "55", "60"], "answer": 0}, {"id": 19277, "question": "if x < y < z and y - x > 3 , where x is an even integer and y and z are odd integers , what is the least possible value of z - x ?", "options": ["7", "6", "8", "9", "10"], "answer": 0}, {"id": 32412, "question": "the cost price of an article is 64 % of the marked price . calculate the gain percent after allowing a discount of 25 % ?", "options": ["37.5 %", "37.6 %", "38.5 %", "17.1 %", "37.2 %"], "answer": 3}, {"id": 32027, "question": "in an examination , 25 % of total students failed in hindi , 35 % failed in english and 40 % in both . the percentage of these who passed in both the subjects is :", "options": ["10 %", "20 %", "60 %", "80 %", "50 %"], "answer": 3}, {"id": 18357, "question": "two alloys a and b are composed of two basic elements . the ratios of the compositions of the two basic elements in the two alloys are 5 : 3 and 5 : 1 , respectively . a new alloy x is formed by mixing the two alloys a and b in the ratio 4 : 3 . what is the ratio of the composition of the two basic elements in alloy x ?", "options": ["1 : 1", "2 : 3", "5 : 2", "4 : 3", "7 : 9"], "answer": 2}, {"id": 31610, "question": "there are two concentric circles with radii 6 and 4 . if the radius of the outer circle is increased by 50 % and the radius of the inner circle decreased by 25 % , by what percent does the area between the circles increase ?", "options": ["160", "210", "260", "310", "360"], "answer": 2}, {"id": 6989, "question": "the diagonals of a rhombus are 12 cm and 10 cm . find its area ?", "options": ["158", "129", "150", "123", "60"], "answer": 4}, {"id": 3664, "question": "what percent of 10 is 10 percent of 1 ?", "options": ["0.1 %", "1 %", "10 %", "90 %", "100 %"], "answer": 1}]