[{"id": 30844, "question": "robert ' s salary was decreased by 60 % and subsequently increased by 60 % . how much percentage does he lose ?", "options": ["10 %", "20 %", "25 %", "36 %", "50 %"], "answer": 3}, {"id": 425, "question": "p is able to do a piece of work in 10 days and q can do the same work in 12 days . if they can work together for 5 days , what is the fraction of work left ?", "options": ["7 / 12", "5 / 12", "1 / 12", "3 / 12", "1 / 2"], "answer": 2}, {"id": 8040, "question": "because he \u2019 s taxed by his home planet , mork pays a tax rate of 45 % on his income , while mindy pays a rate of only 15 % on hers . if mindy earned 4 times as much as mork did , what was their combined tax rate ?", "options": ["19 %", "21 %", "23 %", "25 %", "27 %"], "answer": 1}, {"id": 9729, "question": "find compound interest on $ 8000 at 15 % per annum for 2 years 4 months , compounded annually .", "options": ["3109", "3209", "3108", "3107", "3100"], "answer": 0}, {"id": 11281, "question": "steve traveled the first 2 hours of his journey at 50 mph and the last 3 hours of his journey at 80 mph . what is his average speed of travel for the entire journey ?", "options": ["68 mph", "56.67 mph", "60 mph", "64 mph", "66.67 mph"], "answer": 0}, {"id": 17999, "question": "a train running at the speed of 180 km / hr crosses a pole in 36 seconds . what is the length of the train ?", "options": ["450 m", "500 m", "550 m", "600 m", "650 m"], "answer": 3}, {"id": 32123, "question": "the average salary of all the workers in a workshop is rs . 9000 . the average salary of 6 technicians is rs . 12000 and the average salary of the rest is rs . 6000 . the total number of workers in the workshop is ?", "options": ["23", "21", "52", "56", "12"], "answer": 4}, {"id": 5716, "question": "the area of a triangle is with base 8.4 m and height 5.8 m ?", "options": ["11.36 m 2", "10.36 m 2", "18.36 m 2", "19.36 m 2", "24.36 m 2"], "answer": 4}, {"id": 1308, "question": "consider the sets tn = { n , n + 1 , n + 2 , n + 3 , n + 4 ) , where n = 1 , 2 , 3 , \u2026 , 96 . how many of these sets contain 6 or any integral multiple thereof ( i . e . , any one of the numbers 6 , 12 , 18 , \u2026 ) ?", "options": ["80", "81", "82", "83", "84"], "answer": 0}, {"id": 6814, "question": "while working alone at their constant rates , computer x can process 240 files in 4 hours , and computer y can process 240 files in 6 hours . if all files processed by these computers are the same size , how many hours would it take the two computers , working at the same time at their respective constant rates , to process a total of 240 files ?", "options": ["2", "2.2", "2.4", "2.6", "2.8"], "answer": 2}, {"id": 31437, "question": "12 : 8 seconds : : ? : 4 minutes", "options": ["10", "15", "6", "8", "7"], "answer": 2}, {"id": 13657, "question": "a bottle contains a certain solution . in the bottled solution , the ratio of water to soap is 3 : 2 , and the ratio of soap to salt is four times this ratio . the solution is poured into an open container , and after some time , the ratio of water to soap in the open container is halved by water evaporation . at that time , what is the ratio of water to salt in the solution ?", "options": ["1 : 1", "2 : 3", "3 : 2", "9 : 4", "36 : 8"], "answer": 4}, {"id": 30667, "question": "a flagpole 18 meters high casts a shadow of length 45 meters . if a building under similar conditions casts a shadow of length 50 meters , what is the height of the building ( in meters ) ?", "options": ["16", "20", "24", "28", "32"], "answer": 1}, {"id": 15325, "question": "if sushi rows 27 km upstream and 81 km down steam taking 9 hours each , then the speed of the stream", "options": ["12 kmph", "13 kmph", "22 kmph", "20 kmph", "15 kmph"], "answer": 0}, {"id": 13176, "question": "kamal obtained 76 , 60 , 72 , 65 and 82 marks ( out of 100 ) in english , mathematics , physics , chemistry and biology . what are his average marks ?", "options": ["71", "69", "72", "75", ""], "answer": 0}, {"id": 14048, "question": "a store owner estimates that the average price of type a products will increase by 15 % next year and that the price of type b products will increase by 18 % next year . this year , the total amount paid for type a products was $ 4600 and the total price paid for type b products was $ 8400 . according to the store owner ' s estimate , and assuming the number of products purchased next year remains the same as that of this year , how much will be spent for both products next year ?", "options": ["$ 15,202", "$ 15,325", "$ 16,000", "$ 16,225", "$ 17,155"], "answer": 0}, {"id": 5868, "question": "the value of a scooter depreciates in such a way that its value of the end of each year is 3 / 4 of its value of the beginning of the same year . if the initial value of the scooter is rs . 40,000 , what is the value at the end of 1 year ?", "options": ["3277", "2977", "30000", "6077", "17112"], "answer": 2}, {"id": 15644, "question": "it is well known that a triangle \u2019 s area is \u221a ( p ( p - a ) ( p - b ) ( p - c ) ) , when p = ( a + b + c ) / 2 , such that a , b , c are the lengths of sides of the triangle . if the triangle has 300 , 300 , and 300 as the side \u2019 s lengths , what is the triangle \u2019 s area ?", "options": ["34,200", "36,200", "38,200", "42,200", "38,971"], "answer": 4}, {"id": 23097, "question": "the ratio of boarders to day students at a school was originally 2 to 5 . however , after a number of new boarders join the initial 60 boarders , the ratio changed to 1 to 2 . if no boarders became day students and vice versa , and no students left the school , how many new boarders joined the school ?", "options": ["12", "15", "20", "24", "30"], "answer": 1}, {"id": 7637, "question": "keats library purchases a number of new books , all in the category of biography , and the library does not acquire any other books . with the addition of the new biographies , the biography collection of the library amounts to 32 % of the total number of books in the library . if prior to the purchase , only 20 % of the books in keats library were biographies , by what percent has the number of biographies in the library increased ?", "options": ["60 %", "72 %", "88 %", "95 %", "110 %"], "answer": 2}, {"id": 16697, "question": "how many 4 - digit positive integers are there , where each digit is positive , and no 3 adjacent digits are same ?", "options": ["1236", "3528", "4096", "4608", "6561"], "answer": 1}, {"id": 32645, "question": "in \u03b4 pqs above , if pq = 7 and ps = 8 , then", "options": ["9 / 4", "12 / 5", "56 / 9", "15 / 4", "20 / 3"], "answer": 2}, {"id": 25490, "question": "a cylindrical can has a radius of 3 centimeters and a height of 12 centimeters . what is the area , in square centimeters , of a rectangular label that completely covers the curved surface of the can without over - lapping ?", "options": ["16 pi", "72 pi", "96 pi", "192 pi", "576 pi"], "answer": 1}, {"id": 8413, "question": "sonika bought a v . c . r . at the list price of 18,600 . if the rate of sales tax was 8 % , find the amount she had to pay for purchasing the v . c . r .", "options": ["20,088", "19,780", "19,680", "19,380", ""], "answer": 0}, {"id": 9978, "question": "3 / 4 of 1 / 2 of 2 / 5 of 5040 = ?", "options": ["392", "229", "756", "493", "540"], "answer": 2}, {"id": 6922, "question": "a chemical supply company has 60 liters of a 30 % hno 3 solution . how many liters of pure undiluted hno 3 must the chemists add so that the resultant solution is a 50 % solution ?", "options": ["12", "15", "20", "24", "30"], "answer": 3}, {"id": 23938, "question": "a boat running downstream covers a distance of 12 km in 2 hours while for covering the same distance upstream , it takes 3 hours . what is the speed of the boat in still water ?", "options": ["8 kmph", "5 kmph", "4 kmph", "6 kmph", "7 kmph"], "answer": 1}, {"id": 25519, "question": "working alone at its constant rate , machine a produces x boxes in 10 minutes and working alone at its constant rate , machine b produces 2 x boxes in 5 minutes . how many minutes does it take machines a and b , working simultaneously at their respective constant rates , to produce 7 x boxes ?", "options": ["3 minut", "4 minut", "5 minut", "14 minut", "s"], "answer": 3}, {"id": 2260, "question": "a money lender finds that due to a fall in the annual rate of interest from 8 % to 7 2 / 7 % his yearly income diminishes by rs . 61.50 . his capital is", "options": ["22.378", "87.86", "246.0", "78.88", "127.71"], "answer": 1}, {"id": 25982, "question": "one night a certain hotel rented 1 / 2 of its rooms , including 2 / 3 of their air conditioned rooms . if 3 / 5 of its rooms were air conditioned , what percent of the rooms that were not rented were air conditioned ?", "options": ["25 %", "30 %", "35 %", "40 %", "50 %"], "answer": 3}, {"id": 14774, "question": "what number is obtained by adding the units digits of 734 ^ 99 and 347 ^ 82 ?", "options": ["10", "11", "12", "13", "14"], "answer": 3}, {"id": 31500, "question": "if m is a positive integer and m ^ 2 is divisible by 39 , then the largest positive integer that must divide m is ?", "options": ["3", "6", "8", "12", "13"], "answer": 4}, {"id": 17192, "question": "the width of a rectangular hall is \u00bd of its length . if the area of the hall is 288 sq . m , what is the difference between its length and breadth ?", "options": ["8 m", "10 m", "12 m", "15 m", "17 m"], "answer": 2}, {"id": 22427, "question": "if x = 3 y , where y is a prime number greater than 2 , how many different positive even divisors does x have , including x ?", "options": ["tion giv", "", "", "from th", "n"], "answer": 0}, {"id": 3051, "question": "if \u221a 10 = 3.16 , find the value of if \u221a 5 / 2", "options": ["1.3", "1.58", "2.03", "2.15", "3.15"], "answer": 1}, {"id": 14702, "question": "a man took loan from a bank at the rate of 12 % p . a . s . i . after 20 years he had to pay rs . 2100 interest only for the period . the principal amount borrowed by him was ?", "options": ["600", "715", "600", "875", "900"], "answer": 3}, {"id": 19860, "question": "for each color copy , print shop x charges $ 1.20 and print shop y charges $ 1.70 . how much greater is the charge for 70 color copies at print shop y than at print shop x ?", "options": ["$ 27", "$ 29", "$ 31", "$ 33", "$ 35"], "answer": 4}, {"id": 12872, "question": "if log 1087.5 = 3.9421 , then the number of digits in ( 875 ) 10 is ?", "options": ["30", "28", "27", "50", "25"], "answer": 3}, {"id": 20745, "question": "someone on a skateboard is traveling 10 miles per hour . how many feet does she travel in 20 seconds ? ( 1 mile = 5280 feet )", "options": ["292 ft", "293.4 ft", "295 ft", "296 ft", "297 ft"], "answer": 1}, {"id": 17455, "question": "108 . triangle a \u2019 s base is 7 % greater than the base of triangle b , and a \u2019 s height is 7 % less than the height of triangle b . the area of triangle a is what percent less or more than the area of triangle b ?", "options": ["", "1 % l", "h oth", "1 % mor", ""], "answer": 4}, {"id": 12917, "question": "a man engaged a servant on a condition that he ' ll pay rs 90 and also give him a bag at the end of the yr . he served for 9 months and was given a turban and rs 65 . so the price of turban is", "options": ["rs 10", "rs 9", "rs 0", "rs 55", "rs 8"], "answer": 0}, {"id": 15992, "question": "two trains 170 m and 160 m long run at the speed of 60 km / hr and 40 km / hr respectively in opposite directions on parallel tracks . the time which they take to cross each other is ?", "options": ["10.6 s", "18.8 s", "", "10.88 s", ""], "answer": 4}, {"id": 7535, "question": "the ratio of the volumes of two cubes is 27 : 64 . what is the ratio of their total surface areas ?", "options": ["18 : 21', '", "81 : 13', '", "8 : 15', '", "16 : 21', '", "1 : 13']"], "answer": 3}, {"id": 6517, "question": "a courtyard is 18 meter long and 12 meter board is to be paved with bricks of dimensions 12 cm by 6 cm . the total number of bricks required is :", "options": ["16000", "18000", "20000", "30000", ""], "answer": 3}, {"id": 20532, "question": "sandy buys an old scooter for $ 800 and spends $ 200 on its repairs . if sandy sells the scooter for $ 1200 , what is the gain percent ?", "options": ["15 %", "18 %", "20 %", "22 %", "25 %"], "answer": 2}, {"id": 30025, "question": "the average age of 15 men is increased by years when two of them whose ages are 21 years and 23 years are replaced by two new men . the average age of the two new men is", "options": ["22", "37", "99", "38", "27"], "answer": 1}, {"id": 8288, "question": "what percent of 15 is 15 percent of 1 ?", "options": ["0.001", "0.01", "0.1", "1", "101"], "answer": 3}, {"id": 7386, "question": "each month , after jill pays for rent , utilities , food , and other necessary expenses , she has one fifth of her net monthly salary left as discretionary income . of this discretionary income , she puts 30 % into a vacation fund , 20 % into savings , and spends 35 % on eating out and socializing . this leaves her with $ 105 dollar , which she typically uses for gifts and charitable causes . what is jill \u2019 s net monthly salary ?", "options": ["$ 2400", "$ 3200", "$ 3500", "$ 6400", "$ 9600"], "answer": 2}, {"id": 8845, "question": "the salaries of a and b together amount to $ 5000 . a spends 95 % of his salary and b , 85 % of his . if now , their savings are the same , what is a ' s salary ?", "options": ["$ 1000", "$ 1250", "$ 2500", "$ 3500", "$ 3750"], "answer": 4}, {"id": 15527, "question": "working together , wayne and his son can shovel the entire driveway in three hours . if wayne can shovel eight times as fast as his son can , how many hours would it take for his son to shovel the entire driveway on his own ?", "options": ["4", "6", "8", "9", "12"], "answer": 3}]